.DS_Store
.gitignore
AUTHORS
ChangeLog
LICENSE
MANIFEST.in
README.md
requirements.txt
setup.cfg
setup.py
test-requirements.txt
docs/readme.txt
etc/sample.conf
minimal_py_setup/__init__.py
minimal_py_setup.egg-info/PKG-INFO
minimal_py_setup.egg-info/SOURCES.txt
minimal_py_setup.egg-info/dependency_links.txt
minimal_py_setup.egg-info/not-zip-safe
minimal_py_setup.egg-info/top_level.txt
tests/__init__.py