Metadata-Version: 1.1
Name: minimal-py-setup
Version: 0.1.dev9.g0575cb3
Summary: summary
Home-page: https://github.com/TheSriram/minimal_py_setup
Author: Sriram Madapusi Vasudevan
Author-email: UNKNOWN
License: UNKNOWN
Platform: UNKNOWN
Classifier: Intended Audience :: Information Technology
Classifier: Intended Audience :: System Administrators
Classifier: Operating System :: POSIX :: Linux
Classifier: Programming Language :: Python
Classifier: Programming Language :: Python :: 2
Classifier: Programming Language :: Python :: 2.7
